{
    "PlayerData": {
        "MindPoints": 0.8409625291824341,
        "MindLevel": 0,
        "CurrentLevel": 0,
        "Money": 0.0,
        "Upgrades": [
            {
                "ID": "AddClickDamageEffect",
                "Level": 1
            },
            {
                "ID": "AddDamagePerSecondTiear1Effect",
                "Level": 0
            }
        ],
        "MindLevelsProgress": [
            {
                "MindPointsForLevelUp": 1.0
            }
        ]
    },
    "intExample": 5,
    "strExample": "Hello!",
    "boolExample": [
        false,
        false,
        false,
        false
    ],
    "idSave": 51
}